pymxml.py
_pymxml.pyd
pymxml-2.8.dist-info/DESCRIPTION.rst
pymxml-2.8.dist-info/METADATA
pymxml-2.8.dist-info/metadata.json
pymxml-2.8.dist-info/RECORD
pymxml-2.8.dist-info/top_level.txt
pymxml-2.8.dist-info/WHEEL
